capdata.py
data/__init__.py
data/curve.py
data/market.py
data/pricing.py
data/refer.py
data/risk.py
request/__init__.py
request/request.py
capdata-1.2.5.dist-info/METADATA
capdata-1.2.5.dist-info/WHEEL
capdata-1.2.5.dist-info/top_level.txt
capdata-1.2.5.dist-info/RECORD
