Metadata-Version: 2.4
Name: capdata
Version: 1.2.5
Summary: capdata  api
Home-page: 
Author: zbz
Requires-Python: >= 3.8.0
Requires-Dist: requests==2.31.0
Requires-Dist: pandas>=2.0.3
Dynamic: author
Dynamic: requires-dist
Dynamic: requires-python
Dynamic: summary
